Metadata-Version: 1.0
Name: fileinfo
Version: 0.3.3
Summary: Show information about files in a tabular fashion.
Home-page: http://www.dinu-gherman.net/
Author: Dinu Gherman
Author-email: gherman@darwin.in-berlin.de
License: GNU General Public Licence v3 (GPLv3)
Download-URL: http://www.dinu-gherman.net/tmp/fileinfo-0.3.3.tar.gz
Keywords: files,attributes,information,tabular display
Platform: Posix
Platform: Windows
Classifier: Development Status :: 3 - Alpha
Classifier: Environment :: Console
Classifier: Intended Audience :: Developers
Classifier: Intended Audience :: End Users/Desktop
Classifier: Intended Audience :: System Administrators
Classifier: License :: OSI Approved :: GNU General Public License (GPL)
Classifier: Operating System :: OS Independent
Classifier: Natural Language :: English
Classifier: Programming Language :: Python
Classifier: Topic :: Utilities
